<?xml version="1.0" encoding="utf-8" ?>
<dwsync>
<file name="db_connection.php" server="C:/xampp/htdocs" local="130855061354824218" remote="130855061350000000" Dst="0" />
<file name="db_connection.php" server="C:/xampp/htdocs/" local="130855061354824218" remote="130855061350000000" Dst="0" />
<file name="session.php" server="C:/xampp/htdocs" local="130862706545800781" remote="130862706540000000" Dst="0" />
<file name="functions.php" server="C:/xampp/htdocs" local="130862834103671875" remote="130862834100000000" Dst="0" />
<file name="session.php" server="C:/xampp/htdocs/" local="130862706545800781" remote="130862706540000000" Dst="0" />
<file name="functions.php" server="C:/xampp/htdocs/" local="130862834103671875" remote="130862834100000000" Dst="0" />
<file name="session.php" server="C:/xampp/htdocs/sites" local="130862706545800781" remote="130862706540000000" Dst="0" />
<file name="db_connection.php" server="C:/xampp/htdocs/sites" local="130855061354824218" remote="130855061350000000" Dst="0" />
<file name="functions.php" server="C:/xampp/htdocs/sites" local="130863065840556640" remote="130863065840000000" Dst="0" />
<file name="db_connection.php" server="C:/xampp/htdocs/sites/" local="130855061354824218" remote="130855061350000000" Dst="0" />
<file name="session.php" server="C:/xampp/htdocs/sites/" local="130863099282607422" remote="130863099280000000" Dst="0" />
</dwsync>